vumi_http_proxy-0.1.1.dist-info/entry_points.txt
vumi_http_proxy-0.1.1.dist-info/metadata.json
vumi_http_proxy-0.1.1.dist-info/METADATA
vumi_http_proxy-0.1.1.dist-info/DESCRIPTION.rst
vumi_http_proxy-0.1.1.dist-info/RECORD
vumi_http_proxy-0.1.1.dist-info/top_level.txt
vumi_http_proxy-0.1.1.dist-info/WHEEL
vumi_http_proxy/__init__.py
vumi_http_proxy/blacklist_reader.py
vumi_http_proxy/servicemaker.py
vumi_http_proxy/queen_of_ni.py
vumi_http_proxy/http_proxy.py
vumi_http_proxy/config_reader.py
vumi_http_proxy/test/__init__.py
vumi_http_proxy/test/test_servicemaker.py
vumi_http_proxy/test/helpers.py
vumi_http_proxy/test/test_queen_of_ni.py
vumi_http_proxy/test/test_http_proxy.py
vumi_http_proxy/test/test_proxy_blacklist.py
twisted/plugins/proxy_worker_starter.py
