Metadata-Version: 2.0
Name: vumi-http-proxy
Version: 0.1.1
Summary: HTTP Proxy in Python Twisted to prevent unauthorized access to blacklisted ips
Home-page: https://github.com/praekelt/vumi-http-proxy
Author: Praekelt Foundation
Author-email: dev@praekeltfoundation.org
License: BSD
Platform: UNKNOWN
Classifier: Intended Audience :: Developers
Classifier: Natural Language :: English
Classifier: Programming Language :: Python :: 2.7
Classifier: Operating System :: OS Independent
Classifier: Topic :: Software Development :: Libraries :: Python Modules
Requires-Dist: zope.interface
Requires-Dist: Click
Requires-Dist: Twisted
Requires-Dist: PyYAML
